{
  "generated_at": "2026-03-08T14:04:23.895497+00:00",
  "dry_run": false,
  "entries": [
    {
      "kind": "baseline",
      "clip_id": "wide1",
      "profile_name": "5120_10M",
      "source_path": "D:\\bigbro\\survey\\raw_videos\\test_base.mp4",
      "output_file": "videos/wide1_5120_10M.mp4",
      "output_path": "D:\\bigbro\\survey\\videos\\wide1_5120_10M.mp4",
      "start_sec": 51.0,
      "duration_sec": 20.0,
      "process_time_sec": 0,
      "size_bytes": 25626860,
      "size_mb": 24.439678
    },
    {
      "kind": "candidate",
      "clip_id": "wide1",
      "profile_name": "3840_SAME",
      "source_path": "D:\\bigbro\\survey\\raw_videos\\test_base.mp4",
      "output_file": "videos/wide1_3840_SAME.mp4",
      "output_path": "D:\\bigbro\\survey\\videos\\wide1_3840_SAME.mp4",
      "start_sec": 51.0,
      "duration_sec": 20.0,
      "process_time_sec": 10.368475,
      "size_bytes": 38017012,
      "size_mb": 36.255848
    },
    {
      "kind": "candidate",
      "clip_id": "wide1",
      "profile_name": "3840_6M",
      "source_path": "D:\\bigbro\\survey\\raw_videos\\test_base.mp4",
      "output_file": "videos/wide1_3840_6M.mp4",
      "output_path": "D:\\bigbro\\survey\\videos\\wide1_3840_6M.mp4",
      "start_sec": 51.0,
      "duration_sec": 20.0,
      "process_time_sec": 8.502445,
      "size_bytes": 13822171,
      "size_mb": 13.181849
    },
    {
      "kind": "candidate",
      "clip_id": "wide1",
      "profile_name": "3840_4M",
      "source_path": "D:\\bigbro\\survey\\raw_videos\\test_base.mp4",
      "output_file": "videos/wide1_3840_4M.mp4",
      "output_path": "D:\\bigbro\\survey\\videos\\wide1_3840_4M.mp4",
      "start_sec": 51.0,
      "duration_sec": 20.0,
      "process_time_sec": 8.161595,
      "size_bytes": 9095127,
      "size_mb": 8.673789
    },
    {
      "kind": "candidate",
      "clip_id": "wide1",
      "profile_name": "3840_BAD",
      "source_path": "D:\\bigbro\\survey\\raw_videos\\test_base.mp4",
      "output_file": "videos/wide1_3840_BAD.mp4",
      "output_path": "D:\\bigbro\\survey\\videos\\wide1_3840_BAD.mp4",
      "start_sec": 51.0,
      "duration_sec": 20.0,
      "process_time_sec": 6.951525,
      "size_bytes": 2123553,
      "size_mb": 2.025178
    },
    {
      "kind": "candidate",
      "clip_id": "wide1",
      "profile_name": "3840_CODEC",
      "source_path": "D:\\bigbro\\survey\\raw_videos\\test_base.mp4",
      "output_file": "videos/wide1_3840_CODEC.mp4",
      "output_path": "D:\\bigbro\\survey\\videos\\wide1_3840_CODEC.mp4",
      "start_sec": 51.0,
      "duration_sec": 20.0,
      "process_time_sec": 17.772168,
      "size_bytes": 12958779,
      "size_mb": 12.358455
    },
    {
      "kind": "baseline",
      "clip_id": "wide2",
      "profile_name": "5120_10M",
      "source_path": "D:\\bigbro\\survey\\raw_videos\\6492.mp4",
      "output_file": "videos/wide2_5120_10M.mp4",
      "output_path": "D:\\bigbro\\survey\\videos\\wide2_5120_10M.mp4",
      "start_sec": 60.0,
      "duration_sec": 20.0,
      "process_time_sec": 0,
      "size_bytes": 18394078,
      "size_mb": 17.54196
    },
    {
      "kind": "candidate",
      "clip_id": "wide2",
      "profile_name": "3840_SAME",
      "source_path": "D:\\bigbro\\survey\\raw_videos\\6492.mp4",
      "output_file": "videos/wide2_3840_SAME.mp4",
      "output_path": "D:\\bigbro\\survey\\videos\\wide2_3840_SAME.mp4",
      "start_sec": 60.0,
      "duration_sec": 20.0,
      "process_time_sec": 8.391628,
      "size_bytes": 18842379,
      "size_mb": 17.969493
    },
    {
      "kind": "candidate",
      "clip_id": "wide2",
      "profile_name": "3840_6M",
      "source_path": "D:\\bigbro\\survey\\raw_videos\\6492.mp4",
      "output_file": "videos/wide2_3840_6M.mp4",
      "output_path": "D:\\bigbro\\survey\\videos\\wide2_3840_6M.mp4",
      "start_sec": 60.0,
      "duration_sec": 20.0,
      "process_time_sec": 8.007355,
      "size_bytes": 13911441,
      "size_mb": 13.266984
    },
    {
      "kind": "candidate",
      "clip_id": "wide2",
      "profile_name": "3840_4M",
      "source_path": "D:\\bigbro\\survey\\raw_videos\\6492.mp4",
      "output_file": "videos/wide2_3840_4M.mp4",
      "output_path": "D:\\bigbro\\survey\\videos\\wide2_3840_4M.mp4",
      "start_sec": 60.0,
      "duration_sec": 20.0,
      "process_time_sec": 7.547842,
      "size_bytes": 9070580,
      "size_mb": 8.650379
    },
    {
      "kind": "candidate",
      "clip_id": "wide2",
      "profile_name": "3840_BAD",
      "source_path": "D:\\bigbro\\survey\\raw_videos\\6492.mp4",
      "output_file": "videos/wide2_3840_BAD.mp4",
      "output_path": "D:\\bigbro\\survey\\videos\\wide2_3840_BAD.mp4",
      "start_sec": 60.0,
      "duration_sec": 20.0,
      "process_time_sec": 6.099384,
      "size_bytes": 2105167,
      "size_mb": 2.007644
    },
    {
      "kind": "candidate",
      "clip_id": "wide2",
      "profile_name": "3840_CODEC",
      "source_path": "D:\\bigbro\\survey\\raw_videos\\6492.mp4",
      "output_file": "videos/wide2_3840_CODEC.mp4",
      "output_path": "D:\\bigbro\\survey\\videos\\wide2_3840_CODEC.mp4",
      "start_sec": 60.0,
      "duration_sec": 20.0,
      "process_time_sec": 14.720404,
      "size_bytes": 12654425,
      "size_mb": 12.0682
    }
  ]
}
